<?xml version="1.0" encoding="UTF-8"?>

<BootstrapTexts xmlns:xsi="http://www.w3.org/2001/XMLSchema-instance" xsi:noNamespaceSchemaLocation="opencms://system/modules/com.alkacon.bootstrap.schemas/schemas/text.xsd">
  <BootstrapText language="en">
    <Headline><![CDATA[Further login options]]></Headline>
    <Text name="Text0">
      <links>
        <link name="link0" internal="true" type="A">
          <target><![CDATA[/sites/default/login/]]></target>
          <uuid>d87f4764-58f1-11e4-903d-005056b61161</uuid>
        </link>
        <link name="link1" internal="true" type="A">
          <target><![CDATA[/system/login/]]></target>
          <uuid>8247eafb-11b7-11db-91cd-fdbae480bac9</uuid>
        </link>
      </links>
      <content><![CDATA[<p> </p>
<p>Just to be complete, you have the following additonal options to log in:</p>
<p style="padding-left: 30px;"><a href="%(link0)">Log in through the login page of this demo website</a>.<br />A page that also uses the login dialog element shown above.</p>
<p style="padding-left: 30px;"><a href="%(link1)">Log in with the default OpenCms login dialog</a>. <br />This the native log in dialog with more options.</p>]]></content>
    </Text>
    <Link>
      <Text><![CDATA[Continue with Step 1: Modify a page]]></Text>
      <URI>
        <link internal="true" type="WEAK">
          <target><![CDATA[/sites/default/tutorial-new/step-1-modify-a-page/]]></target>
          <uuid>aa24899f-5ae1-11e4-955d-005056b61161</uuid>
        </link>
      </URI>
    </Link>
  </BootstrapText>
</BootstrapTexts>
